{
  "title": "Player 113 (37th Squid Game)",
  "details": {
    "Name": "Unknown",
    "Aliases": "Player 113",
    "Relationships": "Player 117 - Ally and Teammate in Six-Legged Pentathlon. Player 152 - Ally and Teammate in Six-Legged Pentathlon. Player 337 - Ally and Teammate in Six-Legged Pentathlon. Player 340 - Ally and Teammate in Six-Legged Pentathlon.",
    "Affiliation": "Player 113's team Team X",
    "Born": "In 1980's-1990's",
    "Fate": {
      "Status": "Deceased",
      "Died": "November 3–4, 2024 Dormitory, The Island, during Special Game",
      "Cause of death": "Killed by an O player"
    },
    "Physical Description": {
      "Gender": "Female",
      "Eye color": "Dark brown",
      "Hair color": "Black"
    },
    "Appearances": {
      "Portrayed by": "Jang Mi-yung",
      "First appearance": "\"001\"",
      "Last appearance": "\"Friend or Foe\""
    }
  }
}