{
  "title": "Player 135 (37th Squid Game)",
  "Name": "Unknown",
  "Affiliation": "Team O",
  "Fate": {
    "Status": "Deceased",
    "Died": "November 2, 2024\nSix-Legged Pentathlon",
    "Cause of death": "Shot by a soldier after running out of time in the Six-Legged Pentathlon"
  },
  "Physical Description": {
    "Gender": "Male",
    "Hair color": "Black"
  },
  "Appearances": {
    "Portrayed by": "Jeong Yong-hyun",
    "First appearance": "001",
    "Last appearance": "One More Game"
  }
}