{
  "title": "Lee Seung-won",
  "Name": "Lee Seung-won",
  "Aliases": "Player 336",
  "Family": "Unnamed wife\nUnnamed children",
  "Relationships": "Kim Gi-min † (friend and ally)\nPlayer 145 † (former ally, teammate during the Six-Legged Pentathlon)\nPlayer 238 † (teammate during the Six-Legged Pentathlon)\nPlayer 206 † (former ally, teammate during the Six-Legged Pentathlon)\nPlayer 394 † (former ally, victim)\nPlayer 359 † (enemy)\nIm Jeong-dae † (ally)\nKim Yun-tae † (ally)\nLee Myung-gi † (former ally, killer)\nSeong Gi-hun † (savior, enemy)",
  "Affiliation": "37th Squid Game\nSeekers",
  "Fate": {
    "Status": "Deceased",
    "Died": "November 6, 2024\nSky Squid Game",
    "Cause of death": "Pushed off triangle pillar by Lee Myung-gi with pole and fell to death"
  },
  "Physical Description": {
    "Gender": "Male",
    "Eye color": "Black",
    "Hair color": "Black"
  },
  "Appearances": {
    "Portrayed by": "Park Jin-woo",
    "First appearance": "\"001\" (icon)",
    "Last appearance": "Humans Are… (corpse)"
  }
}