{
  "title": "Player 354",
  "data": {
    "Name": "Unknown",
    "Aliases": "Player 354",
    "Affiliation": [
      "37th Squid Game",
      "Team O"
    ]
  },
  "Fate": {
    "Status": "Deceased",
    "Died": [
      "3 November, 2024",
      "Mingle",
      "(error)"
    ],
    "Cause of death": "She died in round 2 probably from being dumped or not getting a room"
  },
  "Physical Description": {
    "Gender": "Female",
    "Eye color": "Dark Brown",
    "Hair color": "Short black hair/Gray hair tied up"
  },
  "Appearances": {
    "Portrayed by": "2 Unknown Extras.",
    "First appearance": "001",
    "Last appearance": "O X"
  }
}